hrver/__init__.py
hrver/api.py
hrver/constants.py
hrver/features.py
hrver/utils.py
hrver/examples/api/__init__.py
hrver/examples/api/databases.py
hrver/examples/app/app.py
hrver-0.0.1.dist-info/LICENSE
hrver-0.0.1.dist-info/METADATA
hrver-0.0.1.dist-info/WHEEL
hrver-0.0.1.dist-info/top_level.txt
hrver-0.0.1.dist-info/RECORD
