Metadata-Version: 2.1
Name: hrver
Version: 0.0.1
Summary: HRV features extraction and PhysioNet databases API for ECG HRV multiclass heart disease machine learning model implementation
Author-email: Ivan Sergienko <err.ernest@mail.ru>
Project-URL: Homepage, https://github.com/I-eerr-I/hrver
Classifier: Programming Language :: Python :: 3
Classifier: License :: OSI Approved :: MIT License
Classifier: Operating System :: OS Independent
Requires-Python: >=3.7
License-File: LICENSE
